<?xml version="1.0" encoding="utf-8" ?>
<XnaContent>
	<!--  idk what asset type is supposed to be  -->
	<Asset Type="MyDataTypes.LevelObjectData[]">
		<!--  Start Objects before first gap  -->

		<!--  Background  -->
		<Item>
			<ObjectType>Background</ObjectType>
			<ObjectName>Background13</ObjectName>
			<Location>0 0</Location>
		</Item>

		<!--  Blocks  -->
		<!--  Left Column  -->
		<Item>
			<ObjectType>Block</ObjectType>
			<ObjectName>DepthBlock</ObjectName>
			<Location>136 132</Location>
		</Item>
		<Item>
			<ObjectType>Block</ObjectType>
			<ObjectName>DepthBlock</ObjectName>
			<Location>136 176</Location>
		</Item>
		<Item>
			<ObjectType>Block</ObjectType>
			<ObjectName>DepthBlock</ObjectName>
			<Location>136 220</Location>
		</Item>
		<Item>
			<ObjectType>Block</ObjectType>
			<ObjectName>DepthBlock</ObjectName>
			<Location>136 264</Location>
		</Item>
		<Item>
			<ObjectType>Block</ObjectType>
			<ObjectName>DepthBlock</ObjectName>
			<Location>136 308</Location>
		</Item>

		<!--  Right Column  -->
		<Item>
			<ObjectType>Block</ObjectType>
			<ObjectName>DepthBlock</ObjectName>
			<Location>622 132</Location>
		</Item>
		<Item>
			<ObjectType>Block</ObjectType>
			<ObjectName>DepthBlock</ObjectName>
			<Location>622 176</Location>
		</Item>
		<Item>
			<ObjectType>Block</ObjectType>
			<ObjectName>DepthBlock</ObjectName>
			<Location>622 220</Location>
		</Item>
		<Item>
			<ObjectType>Block</ObjectType>
			<ObjectName>DepthBlock</ObjectName>
			<Location>622 264</Location>
		</Item>
		<Item>
			<ObjectType>Block</ObjectType>
			<ObjectName>DepthBlock</ObjectName>
			<Location>622 308</Location>
		</Item>

		<!--  Top Row  -->
		<Item>
			<ObjectType>Block</ObjectType>
			<ObjectName>DepthBlock</ObjectName>
			<Location>190 132</Location>
		</Item>
		<Item>
			<ObjectType>Block</ObjectType>
			<ObjectName>DepthBlock</ObjectName>
			<Location>244 132</Location>
		</Item>
		<Item>
			<ObjectType>Block</ObjectType>
			<ObjectName>DepthBlock</ObjectName>
			<Location>298 132</Location>
		</Item>
		<Item>
			<ObjectType>Block</ObjectType>
			<ObjectName>DepthBlock</ObjectName>
			<Location>352 132</Location>
		</Item>
		<Item>
			<ObjectType>Block</ObjectType>
			<ObjectName>DepthBlock</ObjectName>
			<Location>406 132</Location>
		</Item>
		<Item>
			<ObjectType>Block</ObjectType>
			<ObjectName>DepthBlock</ObjectName>
			<Location>460 132</Location>
		</Item>
		<Item>
			<ObjectType>Block</ObjectType>
			<ObjectName>DepthBlock</ObjectName>
			<Location>514 132</Location>
		</Item>
		<Item>
			<ObjectType>Block</ObjectType>
			<ObjectName>DepthBlock</ObjectName>
			<Location>568 132</Location>
		</Item>

		<!--  Bottom Row  -->
		<Item>
			<ObjectType>Block</ObjectType>
			<ObjectName>DepthBlock</ObjectName>
			<Location>190 308</Location>
		</Item>
		<Item>
			<ObjectType>Block</ObjectType>
			<ObjectName>DepthBlock</ObjectName>
			<Location>244 308</Location>
		</Item>
		<Item>
			<ObjectType>Block</ObjectType>
			<ObjectName>DepthBlock</ObjectName>
			<Location>298 308</Location>
		</Item>
		<Item>
			<ObjectType>Block</ObjectType>
			<ObjectName>DepthBlock</ObjectName>
			<Location>460 308</Location>
		</Item>
		<Item>
			<ObjectType>Block</ObjectType>
			<ObjectName>DepthBlock</ObjectName>
			<Location>514 308</Location>
		</Item>
		<Item>
			<ObjectType>Block</ObjectType>
			<ObjectName>DepthBlock</ObjectName>
			<Location>568 308</Location>
		</Item>

		<!--  Statue Blocks  -->
		<Item>
			<ObjectType>Block</ObjectType>
			<ObjectName>StatueOneBlock</ObjectName>
			<Location>298 176</Location>
		</Item>
		<Item>
			<ObjectType>Block</ObjectType>
			<ObjectName>StatueOneBlock</ObjectName>
			<Location>244 220</Location>
		</Item>
		<Item>
			<ObjectType>Block</ObjectType>
			<ObjectName>StatueTwoBlock</ObjectName>
			<Location>460 176</Location>
		</Item>
		<Item>
			<ObjectType>Block</ObjectType>
			<ObjectName>StatueTwoBlock</ObjectName>
			<Location>514 220</Location>
		</Item>

		<!--  Items  -->
		<Item>
			<ObjectType>Item</ObjectType>
			<ObjectName>PurpleTriangle</ObjectName>
			<Location>400 220</Location>
		</Item>
		
		<!--  End Objects before first gap  -->
	</Asset>
</XnaContent>
